bcs/__init__.py
bcs/bootcampspot.py
bcs/errors.py
tests/__init__.py
tests/test_bootcampspot.py
bcs_python-0.0.3.dist-info/LICENSE
bcs_python-0.0.3.dist-info/METADATA
bcs_python-0.0.3.dist-info/WHEEL
bcs_python-0.0.3.dist-info/top_level.txt
bcs_python-0.0.3.dist-info/RECORD
