Metadata-Version: 2.1
Name: bcs-python
Version: 0.0.3
Summary: Python wrapper for Bootcampspot API
Home-page: https://github.com/Ouroboros-analytics/bcs-python
Author: Justin Parker
Author-email: justin.parker.12@gmail.com
License: MIT
Keywords: Bootcampspot API Wrapper
Platform: UNKNOWN
Classifier: Development Status :: 3 - Alpha
Classifier: Programming Language :: Python :: 3
Classifier: License :: OSI Approved :: MIT License
Classifier: Operating System :: OS Independent
